{
  "ID 0": {
    "Centro\u00efde": "LeSoleil",
    "Freq. centroide": 1,
    "Termes": [
      "LeSoleil",
      "LesSuedois",
      "Soleil",
      "leSoleil"
    ]
  },
  "ID 1": {
    "Centro\u00efde": "Lellres",
    "Freq. centroide": 1,
    "Termes": [
      "Eluelqnes",
      "Euvres",
      "Excellence",
      "Jalumet",
      "Lellres",
      "Leperos",
      "ciellEtes",
      "les\u2018praz'"
    ]
  },
  "ID 2": {
    "Centro\u00efde": "Vais",
    "Freq. centroide": 1,
    "Termes": [
      "Aplaisir",
      "Chinois",
      "Danois",
      "Eshis",
      "Inis",
      "Main",
      "Opatas",
      "Pai\u2018tons",
      "Paris",
      "Pouvais",
      "Trois",
      "Unis",
      "Vais",
      "Viva\u00e9it\u00e9",
      "Voisins",
      "Vrir",
      "Wabz'",
      "la.-"
    ]
  },
  "ID 3": {
    "Centro\u00efde": "sions;.jeunes",
    "Freq. centroide": 1,
    "Termes": [
      "sions;.jeunes"
    ]
  },
  "ID 4": {
    "Centro\u00efde": "\u00e9ditioul.4vol.in-1Q",
    "Freq. centroide": 1,
    "Termes": [
      "\u00e9ditioul.4vol.in-1Q"
    ]
  },
  "ID 5": {
    "Centro\u00efde": "Eus\u00e9bio",
    "Freq. centroide": 12,
    "Termes": [
      "Durango",
      "Eus\u00e9bio",
      "N6Eus\u00e9bio",
      "NoEus\u00e9bio",
      "Rosario"
    ]
  },
  "ID 6": {
    "Centro\u00efde": "Europe",
    "Freq. centroide": 3,
    "Termes": [
      "Enrope",
      "Europ'e",
      "Europe",
      "FEYDEAU",
      "Jupiter",
      "i1tomba"
    ]
  },
  "ID 7": {
    "Centro\u00efde": "12\n\n",
    "Freq. centroide": 1,
    "Termes": [
      "-35\n\nDona",
      "12\n\n",
      "199\n\n",
      "37\n\n",
      "415\n\n",
      "65\n\n",
      "do\n\n",
      "\ufb02\n\n"
    ]
  },
  "ID 8": {
    "Centro\u00efde": "PeauxRouges",
    "Freq. centroide": 4,
    "Termes": [
      "Iesunsapres",
      "PeauxBouges",
      "PeauxRonges",
      "PeauxRouges"
    ]
  },
  "ID 9": {
    "Centro\u00efde": "Venaient",
    "Freq. centroide": 1,
    "Termes": [
      "Inenacaient",
      "Parfaitement",
      "Venaient",
      "Versaires",
      "e\ufb01\u2018rayant"
    ]
  },
  "ID 10": {
    "Centro\u00efde": "a\ufb01\u2018ectation",
    "Freq. centroide": 1,
    "Termes": [
      "D\u00e9nomination",
      "a\ufb01\u2018ectation"
    ]
  },
  "ID 11": {
    "Centro\u00efde": "Lu-",
    "Freq. centroide": 1,
    "Termes": [
      "1M.",
      "Ba-",
      "Buf-",
      "In--",
      "LeM",
      "Lhmt",
      "Lu\n\n",
      "Lu-",
      "Lune",
      "Luz",
      "Nul",
      "Pan-",
      "Ra-",
      "Vue",
      "Yeux",
      "sur\u2014-",
      "\u00e9L-"
    ]
  },
  "ID 12": {
    "Centro\u00efde": "VinpubliquedcMontaigne",
    "Freq. centroide": 1,
    "Termes": [
      "VinpubliquedcMontaigne"
    ]
  },
  "ID 13": {
    "Centro\u00efde": "Tout-Puissant",
    "Freq. centroide": 1,
    "Termes": [
      "Tout-Puissant"
    ]
  },
  "ID 14": {
    "Centro\u00efde": "neselles\\tmursai\\l\u2018('~l",
    "Freq. centroide": 1,
    "Termes": [
      "neselles\\tmursai\\l\u2018('~l"
    ]
  },
  "ID 15": {
    "Centro\u00efde": "Teted\u2019Aigle",
    "Freq. centroide": 5,
    "Termes": [
      "LaTeted\u2019Aigle",
      "Teted\u2019Aigle",
      "T\u00e9ted\u2019Aigle"
    ]
  },
  "ID 16": {
    "Centro\u00efde": "Vous",
    "Freq. centroide": 1,
    "Termes": [
      "Allons",
      "Bouges",
      "Congr\u00e9s",
      "Iroquois",
      "Non",
      "Pimas",
      "Toutcs",
      "Votre",
      "Vous",
      "Voyons",
      "You",
      "busqu\u00e9s",
      "forts\u2019",
      "l\u2019oul\u2018e",
      "\u00e9touIT\u00e9",
      "\u2014nous"
    ]
  },
  "ID 17": {
    "Centro\u00efde": "R\u00e9gencesd\u2019Alger",
    "Freq. centroide": 1,
    "Termes": [
      "R\u00e9gencesd\u2019Alger"
    ]
  },
  "ID 18": {
    "Centro\u00efde": "Mexico",
    "Freq. centroide": 7,
    "Termes": [
      "51Mexico",
      "Merced",
      "Merci",
      "Mexi-",
      "Mexico",
      "Mexicos\u2019",
      "Mexique",
      "Mezcal"
    ]
  },
  "ID 19": {
    "Centro\u00efde": "excellent,\u2018nous",
    "Freq. centroide": 1,
    "Termes": [
      "excellent,\u2018nous"
    ]
  },
  "ID 20": {
    "Centro\u00efde": "Am\u00e9riquem\u00e9ridionale",
    "Freq. centroide": 1,
    "Termes": [
      "Am\u00e9riquem\u00e9ridionale"
    ]
  },
  "ID 21": {
    "Centro\u00efde": "l\u2019Am\u00e9rique",
    "Freq. centroide": 1,
    "Termes": [
      "Am\u00e9rique",
      "Am\u00e9riqueduN",
      "l'Am\u00e9rique",
      "l\u2019Afrique",
      "l\u2019Am\u00e9rique"
    ]
  },
  "ID 22": {
    "Centro\u00efde": "Etats-Unis",
    "Freq. centroide": 2,
    "Termes": [
      "EtaLs-Unis",
      "Etats-Unis",
      "Etats-Unisout",
      "Etats\u2014Unis",
      "Etats\u2014Uniss\u2019"
    ]
  },
  "ID 23": {
    "Centro\u00efde": "Indiens",
    "Freq. centroide": 91,
    "Termes": [
      "I\n\nVienne",
      "IndianIe",
      "Indians",
      "Indien",
      "Indiennes",
      "Indiens",
      "LesIndiens",
      "diens",
      "fonddeTeam",
      "maniere",
      "matineen\u2019"
    ]
  },
  "ID 24": {
    "Centro\u00efde": "Ies",
    "Freq. centroide": 1,
    "Termes": [
      "Ame",
      "Apres",
      "DICKENS",
      "Etudes",
      "Ies",
      "Iessalua",
      "Ieurs",
      "Iieues",
      "Incas",
      "I\u00e9gere-",
      "J63",
      "Os",
      "Q23",
      "Vet",
      "ce~",
      "esL",
      "iIs",
      "ins\u2014-"
    ]
  },
  "ID 25": {
    "Centro\u00efde": "Splendide",
    "Freq. centroide": 1,
    "Termes": [
      "Prendsgarde",
      "Splendide",
      "Splendides"
    ]
  },
  "ID 26": {
    "Centro\u00efde": "EtatsEuropciens",
    "Freq. centroide": 1,
    "Termes": [
      "EtatsEuropciens"
    ]
  },
  "ID 27": {
    "Centro\u00efde": "C(EURLOYAL",
    "Freq. centroide": 1,
    "Termes": [
      "C(EURLOYAL"
    ]
  },
  "ID 28": {
    "Centro\u00efde": "l\u2019haciendadelMilagro",
    "Freq. centroide": 1,
    "Termes": [
      "al\u2019haciendadelMilagro",
      "l\u2019haciendadelMilagro"
    ]
  },
  "ID 29": {
    "Centro\u00efde": "Vieil",
    "Freq. centroide": 1,
    "Termes": [
      "Jillnmil",
      "Lisezl",
      "Liwetlu",
      "Victime",
      "Vidala",
      "Vieil",
      "Vieille",
      "Vieux",
      "eifel"
    ]
  },
  "ID 30": {
    "Centro\u00efde": "niqnedosFamillcs",
    "Freq. centroide": 1,
    "Termes": [
      "niqnedosFamillcs"
    ]
  },
  "ID 31": {
    "Centro\u00efde": "Canadien",
    "Freq. centroide": 14,
    "Termes": [
      "Canadian",
      "Canadien",
      "Canadienne",
      "CetEden",
      "Ganadien",
      "oc\u00e9anPaci\ufb01-"
    ]
  },
  "ID 32": {
    "Centro\u00efde": "Cueur",
    "Freq. centroide": 1,
    "Termes": [
      "Aguilar",
      "Cher",
      "Cmur",
      "Coeur",
      "Cueur",
      "CueurLoyal",
      "Docleur",
      "Grandeur",
      "Iecteur",
      "tu?1ui"
    ]
  },
  "ID 33": {
    "Centro\u00efde": "pistedesComanches",
    "Freq. centroide": 2,
    "Termes": [
      "campdesComanches",
      "pistedesComanches"
    ]
  },
  "ID 34": {
    "Centro\u00efde": "Belhumeur",
    "Freq. centroide": 34,
    "Termes": [
      "59\n\nBelhumeur",
      "Belhumeur",
      "Bellmmeur"
    ]
  },
  "ID 35": {
    "Centro\u00efde": "Blancs",
    "Freq. centroide": 3,
    "Termes": [
      "Blanche",
      "Blancs",
      "Blancs-Y",
      "France",
      "Guaymas",
      "Milagro",
      "Oc\u00e9ans",
      "enfonc\u00e9",
      "plaine\n\n"
    ]
  },
  "ID 36": {
    "Centro\u00efde": "TBAPPEUPtS\n\n",
    "Freq. centroide": 1,
    "Termes": [
      "TBAPPEUPtS\n\n"
    ]
  },
  "ID 37": {
    "Centro\u00efde": "Guadalaxm'",
    "Freq. centroide": 1,
    "Termes": [
      "Guadalaxm'",
      "Guadeloupe"
    ]
  },
  "ID 38": {
    "Centro\u00efde": "Conf\u00e9d\u00e9rations\u2019",
    "Freq. centroide": 1,
    "Termes": [
      "Conf\u00e9d\u00e9rations\u2019"
    ]
  },
  "ID 39": {
    "Centro\u00efde": "Tenez",
    "Freq. centroide": 1,
    "Termes": [
      "Arretez",
      "Consez'",
      "Deferez",
      "Prenez",
      "Remettez",
      "Tachez",
      "Tenez",
      "Venez"
    ]
  },
  "ID 40": {
    "Centro\u00efde": "Mexicains",
    "Freq. centroide": 28,
    "Termes": [
      "Am\u00e9ricains",
      "Iesmains",
      "Lancerosmexicains",
      "Mexicains",
      "Mississipi",
      "Voyageursmexicains",
      "capitaine"
    ]
  },
  "ID 41": {
    "Centro\u00efde": "111.1anCHEFS",
    "Freq. centroide": 1,
    "Termes": [
      "111.1anCHEFS"
    ]
  },
  "ID 42": {
    "Centro\u00efde": "pistedelaT\u00e9ted\u2019Aigle",
    "Freq. centroide": 1,
    "Termes": [
      "pistedelaT\u00e9ted\u2019Aigle"
    ]
  },
  "ID 43": {
    "Centro\u00efde": "Ouaklehno",
    "Freq. centroide": 1,
    "Termes": [
      "Ouaklehno",
      "Ouaktehno"
    ]
  },
  "ID 44": {
    "Centro\u00efde": "grandeCanadienne",
    "Freq. centroide": 1,
    "Termes": [
      "grandeCanadienne"
    ]
  },
  "ID 45": {
    "Centro\u00efde": "Gambusinos",
    "Freq. centroide": 1,
    "Termes": [
      "Gambusino",
      "Gambusinos",
      "Gambusi\u2014",
      "gambusinos"
    ]
  },
  "ID 46": {
    "Centro\u00efde": "GrandChefdesAucas",
    "Freq. centroide": 1,
    "Termes": [
      "GrandChefdesAucas"
    ]
  },
  "ID 47": {
    "Centro\u00efde": "Echosdel'Ame",
    "Freq. centroide": 1,
    "Termes": [
      "Echosdel'Ame"
    ]
  },
  "ID 48": {
    "Centro\u00efde": "Izacz'endas-\u2014fermes",
    "Freq. centroide": 1,
    "Termes": [
      "Izacz'endas-\u2014fermes"
    ]
  },
  "ID 49": {
    "Centro\u00efde": "Espagnol",
    "Freq. centroide": 1,
    "Termes": [
      "Compagnon",
      "Espagnol",
      "Espagnols",
      "Esp\u00e9rerl",
      "L'Espaane"
    ]
  },
  "ID 50": {
    "Centro\u00efde": "d\u00e9dain;i1se",
    "Freq. centroide": 1,
    "Termes": [
      "d\u00e9dain;i1se"
    ]
  },
  "ID 51": {
    "Centro\u00efde": "Etat",
    "Freq. centroide": 2,
    "Termes": [
      "Elan",
      "Etat",
      "Etats\u2014",
      "etl\u2019",
      "tOt",
      "udad"
    ]
  },
  "ID 52": {
    "Centro\u00efde": "Napoll\u2018onitSam1",
    "Freq. centroide": 1,
    "Termes": [
      "Napoll\u2018onitSam1"
    ]
  },
  "ID 53": {
    "Centro\u00efde": "Aigles\u2019avanga",
    "Freq. centroide": 1,
    "Termes": [
      "Aigles\u2019avanga"
    ]
  },
  "ID 54": {
    "Centro\u00efde": "L\u2019AngtelerreanM",
    "Freq. centroide": 1,
    "Termes": [
      "L\u2019AngtelerreanM"
    ]
  },
  "ID 55": {
    "Centro\u00efde": "EmpireIrritannique",
    "Freq. centroide": 1,
    "Termes": [
      "EmpireIrritannique"
    ]
  },
  "ID 56": {
    "Centro\u00efde": "Moyen",
    "Freq. centroide": 1,
    "Termes": [
      "Lnnmmmn",
      "Loyal",
      "MnyenAge",
      "Mocksens",
      "Moyen",
      "Providence",
      "Soyez",
      "b\ufb01cher"
    ]
  },
  "ID 57": {
    "Centro\u00efde": "c\u2018est",
    "Freq. centroide": 1,
    "Termes": [
      "Ernest",
      "Ouest\u2014",
      "chevaI",
      "c\u2018est",
      "n\u2019h\u00e9sita",
      "s\u2018est"
    ]
  },
  "ID 58": {
    "Centro\u00efde": "Cordoue",
    "Freq. centroide": 1,
    "Termes": [
      "Carthage",
      "Cordill\u00e9res",
      "Cordoue",
      "Inajordome",
      "Lorsqu\u2019",
      "Pardonnez",
      "Syracuse",
      "merNone",
      "nord\u2014ouest",
      "so].\n\nMore"
    ]
  },
  "ID 59": {
    "Centro\u00efde": "AigleitnoEus\u00e9bio",
    "Freq. centroide": 1,
    "Termes": [
      "AigleitnoEus\u00e9bio"
    ]
  },
  "ID 60": {
    "Centro\u00efde": "Utique",
    "Freq. centroide": 1,
    "Termes": [
      "Azt\u00e9ques",
      "Paci\ufb01que",
      "Utique"
    ]
  },
  "ID 61": {
    "Centro\u00efde": "Comanches",
    "Freq. centroide": 43,
    "Termes": [
      "Comanche",
      "Comanches",
      "Comanches\n\nDE",
      "Comanchesetles",
      "Comanchess\u2019"
    ]
  },
  "ID 62": {
    "Centro\u00efde": "ROMIEUOIadnmc",
    "Freq. centroide": 1,
    "Termes": [
      "ROMIEUOIadnmc"
    ]
  },
  "ID 63": {
    "Centro\u00efde": "Bil",
    "Freq. centroide": 1,
    "Termes": [
      "Belh",
      "Bil",
      "Ciel",
      "Livr'",
      "Ohl",
      "diL",
      "fil\u2019",
      "mo~",
      "ohI",
      "vic~",
      "\u2014il"
    ]
  },
  "ID 64": {
    "Centro\u00efde": "jardindesOli\u2014",
    "Freq. centroide": 1,
    "Termes": [
      "jardindesOli\u2014"
    ]
  },
  "ID 65": {
    "Centro\u00efde": "RioGila",
    "Freq. centroide": 1,
    "Termes": [
      "BioGila",
      "RioGila",
      "WRANGEL",
      "duRioGila"
    ]
  },
  "ID 66": {
    "Centro\u00efde": "golfedoCali-",
    "Freq. centroide": 1,
    "Termes": [
      "golfedoCali-"
    ]
  },
  "ID 67": {
    "Centro\u00efde": "laBourgeoisie",
    "Freq. centroide": 1,
    "Termes": [
      "laBourgeoisie"
    ]
  },
  "ID 68": {
    "Centro\u00efde": "LeCouvx'e\u2014Il\u2018eu",
    "Freq. centroide": 1,
    "Termes": [
      "LeCouvx'e\u2014Il\u2018eu"
    ]
  },
  "ID 69": {
    "Centro\u00efde": "Vages",
    "Freq. centroide": 1,
    "Termes": [
      "Aigles\u2019",
      "Apaches",
      "Manes",
      "Naples",
      "Rafael",
      "Rafa\u00e9l",
      "Sables",
      "Vage",
      "Vages",
      "Visages",
      "Vitr\u00e9es",
      "Yankees",
      "efTet"
    ]
  },
  "ID 70": {
    "Centro\u00efde": "LesLionnesdeParis",
    "Freq. centroide": 1,
    "Termes": [
      "LesLionnesdeParis"
    ]
  },
  "ID 71": {
    "Centro\u00efde": "Babillard",
    "Freq. centroide": 3,
    "Termes": [
      "Babillard",
      "LeBabillard",
      "leBabillard"
    ]
  },
  "ID 72": {
    "Centro\u00efde": "lll~8",
    "Freq. centroide": 1,
    "Termes": [
      "Elll'",
      "Ill\u20148",
      "R\u00e9vnlullon",
      "in~8",
      "llSB",
      "lll~8",
      "l\u2018lbs"
    ]
  },
  "ID 73": {
    "Centro\u00efde": "Babillardcommenga",
    "Freq. centroide": 1,
    "Termes": [
      "Babillardcommenga"
    ]
  },
  "ID 74": {
    "Centro\u00efde": "cath\u00e9draledeMexico",
    "Freq. centroide": 1,
    "Termes": [
      "cath\u00e9draledeMexico"
    ]
  },
  "ID 75": {
    "Centro\u00efde": "Cele",
    "Freq. centroide": 1,
    "Termes": [
      "Aigle",
      "Cele",
      "Cesse",
      "Cette",
      "Chefs",
      "C\u00e9lc\u2019",
      "Helene",
      "Russe",
      "eUe",
      "el",
      "meme",
      "selle",
      "sel\u2019",
      "\u00e9tl\u2018e",
      "\u2014elle",
      "\u2014t\u2014elle"
    ]
  },
  "ID 76": {
    "Centro\u00efde": "I\u2019",
    "Freq. centroide": 1,
    "Termes": [
      "As\u2019",
      "E-",
      "EL",
      "I",
      "IK",
      "Ia",
      "Ie",
      "Ij\u2019",
      "In",
      "Iza",
      "I\u2019",
      "La",
      "L\u2019",
      "Pz'",
      "U11",
      "WEILL",
      "lQ",
      "n\u2019",
      "v0",
      "\u00e9mt\u2019"
    ]
  },
  "ID 77": {
    "Centro\u00efde": "Mexicaine,1\u2019EtatdeSonora",
    "Freq. centroide": 1,
    "Termes": [
      "Mexicaine,1\u2019EtatdeSonora"
    ]
  },
  "ID 78": {
    "Centro\u00efde": "S",
    "Freq. centroide": 2,
    "Termes": [
      "A",
      "A-",
      "E",
      "Eh",
      "F",
      "H",
      "N",
      "Q51",
      "S",
      "SC",
      "SOi",
      "Sar",
      "Sins",
      "Y",
      "amSI",
      "ltS",
      "\u00bb",
      "\u2019"
    ]
  },
  "ID 79": {
    "Centro\u00efde": "l\u2019\ufb01acz\u2019ena\u2019",
    "Freq. centroide": 1,
    "Termes": [
      "l\u2019\ufb01acz\u2019ena\u2019"
    ]
  },
  "ID 80": {
    "Centro\u00efde": "T\u00e9te",
    "Freq. centroide": 3,
    "Termes": [
      "Ph\u00e9b\u00e9",
      "Rome",
      "Tete",
      "T\u00e9le",
      "T\u00e9te",
      "T\u00e9ted\u2019",
      "b\u00e9tie"
    ]
  },
  "ID 81": {
    "Centro\u00efde": "Plateros",
    "Freq. centroide": 2,
    "Termes": [
      "Angleterre",
      "Graturu\u00bb",
      "Plateros",
      "Squatters"
    ]
  },
  "ID 82": {
    "Centro\u00efde": "SierraM",
    "Freq. centroide": 1,
    "Termes": [
      "Chimborazo",
      "SierraM",
      "SierraMadre",
      "Sonora"
    ]
  },
  "ID 83": {
    "Centro\u00efde": "Francais",
    "Freq. centroide": 1,
    "Termes": [
      "Arkansas",
      "Femnwau",
      "Francais",
      "Franeais",
      "Frangais",
      "Fraucoisl",
      "Fraugais",
      "grandscris",
      "voudrais"
    ]
  },
  "ID 84": {
    "Centro\u00efde": "Vastessolitudes",
    "Freq. centroide": 1,
    "Termes": [
      "Vastessolitudes"
    ]
  },
  "ID 85": {
    "Centro\u00efde": "del\u2019ha\u2014\n\ncienda",
    "Freq. centroide": 1,
    "Termes": [
      "del\u2019ha\u2014\n\ncienda"
    ]
  },
  "ID 86": {
    "Centro\u00efde": "unenouvelleespece",
    "Freq. centroide": 1,
    "Termes": [
      "unenouvelleespece"
    ]
  }
}