{
  "ID 0": {
    "Centro\u00efde": "Abientot",
    "Freq. centroide": 1,
    "Termes": [
      "Abienlot",
      "Abientot",
      "Attention",
      "Pasencoe",
      "Washington",
      "bient0ot",
      "bient0tl"
    ]
  },
  "ID 1": {
    "Centro\u00efde": "Voil",
    "Freq. centroide": 3,
    "Termes": [
      "Amoil",
      "Louisl",
      "Nord",
      "Quoil",
      "Toul",
      "Voil",
      "Voilh",
      "Voili",
      "\u2019iil"
    ]
  },
  "ID 2": {
    "Centro\u00efde": "Angelebien-aimeel",
    "Freq. centroide": 1,
    "Termes": [
      "Angelebien-aimeel"
    ]
  },
  "ID 3": {
    "Centro\u00efde": "voudraislMatheueusement",
    "Freq. centroide": 1,
    "Termes": [
      "voudraislMatheueusement"
    ]
  },
  "ID 4": {
    "Centro\u00efde": "Dieul",
    "Freq. centroide": 2,
    "Termes": [
      "Adieul",
      "Bleu7",
      "Damel",
      "Dieppe",
      "Dieul",
      "Eaeal",
      "Mieux",
      "N'esl",
      "lFeul"
    ]
  },
  "ID 5": {
    "Centro\u00efde": "Jevois",
    "Freq. centroide": 1,
    "Termes": [
      "JeIevois",
      "Jed6fie",
      "Jereconnais",
      "Jevois",
      "Lecops"
    ]
  },
  "ID 6": {
    "Centro\u00efde": "Fortbienl",
    "Freq. centroide": 2,
    "Termes": [
      "C'0taienl",
      "Fortbienl",
      "FortbienlPrenez",
      "Iortement"
    ]
  },
  "ID 7": {
    "Centro\u00efde": "LLL",
    "Freq. centroide": 1,
    "Termes": [
      ".LLL",
      "2LLEL",
      "ALLZL",
      "BBLLL",
      "BLLLL",
      "ELLL",
      "HELLlE",
      "ILLL",
      "L.L",
      "L.yLL",
      "LAi",
      "LE6AlL",
      "LL",
      "LL\nH",
      "LL,5",
      "LL.:5",
      "LLA",
      "LLC",
      "LLCLL",
      "LLI",
      "LLL",
      "LLR",
      "LLTL",
      "LLs",
      "LRi",
      "WIL",
      "c;P",
      "cCZCZL",
      "xEL"
    ]
  },
  "ID 8": {
    "Centro\u00efde": "I\n\n1",
    "Freq. centroide": 9,
    "Termes": [
      "1\n\nM",
      "1A\n\n1",
      "E\n\n1",
      "I\n\n1",
      "I\n\n1I",
      "I\n\n1Ni",
      "I\n\nZ1",
      "I\n\nas",
      "I\nI.",
      "I\nW\nG",
      "I.\n\n1",
      "IH\n\niC",
      "IKa\n\n:",
      "IM,1",
      "JI\n\n1",
      "LI\n\nH",
      "MIn\n\n1",
      "N\n\n1",
      "N\n\nE",
      "n\n\n1",
      "rs''1",
      "t\n\n132",
      "\u00ac\n\nS"
    ]
  },
  "ID 9": {
    "Centro\u00efde": "AnomuIdemainere",
    "Freq. centroide": 1,
    "Termes": [
      "AnomuIdemainere"
    ]
  },
  "ID 10": {
    "Centro\u00efde": "sefioPalamede",
    "Freq. centroide": 1,
    "Termes": [
      "sefioPalamede"
    ]
  },
  "ID 11": {
    "Centro\u00efde": "Absolumentlout",
    "Freq. centroide": 1,
    "Termes": [
      "Absolumentlout"
    ]
  },
  "ID 12": {
    "Centro\u00efde": "capRosier",
    "Freq. centroide": 1,
    "Termes": [
      "Capitainel",
      "Mlonsieur",
      "Rapportez",
      "capRosier",
      "capduChat"
    ]
  },
  "ID 13": {
    "Centro\u00efde": "Rameau-",
    "Freq. centroide": 2,
    "Termes": [
      "Raieau",
      "Rameau-",
      "Rameu",
      "Rameun",
      "Ramneau-d'Or",
      "Rampant",
      "Royal-",
      "calme7Deux"
    ]
  },
  "ID 14": {
    "Centro\u00efde": "FORTDUQUESNE",
    "Freq. centroide": 1,
    "Termes": [
      "FORTDUQUESNE"
    ]
  },
  "ID 15": {
    "Centro\u00efde": "ABeauregard",
    "Freq. centroide": 1,
    "Termes": [
      "ABeauregard",
      "Beauregad"
    ]
  },
  "ID 16": {
    "Centro\u00efde": "Maige",
    "Freq. centroide": 1,
    "Termes": [
      "Arive",
      "Gaaiage",
      "Gaiete",
      "Gcagse",
      "Iatigue",
      "Mackay",
      "Maige",
      "Malgre",
      "Marine",
      "Martyisez",
      "Maudite",
      "Meschacebe",
      "Mssacrel",
      "eC01e"
    ]
  },
  "ID 17": {
    "Centro\u00efde": "Grigny",
    "Freq. centroide": 12,
    "Termes": [
      "Carignan",
      "Gigny",
      "Grighy",
      "Grigny",
      "Grigy",
      "baondeGrigny",
      "tgrr2n5"
    ]
  },
  "ID 18": {
    "Centro\u00efde": "Eil-de-Bceuf",
    "Freq. centroide": 1,
    "Termes": [
      "Eil-de-Bceuf"
    ]
  },
  "ID 19": {
    "Centro\u00efde": "l3erger",
    "Freq. centroide": 1,
    "Termes": [
      "Berger",
      "Bergerl",
      "l3eger",
      "l3erge",
      "l3erger"
    ]
  },
  "ID 20": {
    "Centro\u00efde": "Indiens",
    "Freq. centroide": 95,
    "Termes": [
      "Ehbien2",
      "Idiens",
      "Indien",
      "Indiennes",
      "Indiens",
      "Inieux",
      "Inliens",
      "Insouciants",
      "Inuimurai",
      "Iontiere",
      "L'Indien",
      "LesIndiensl",
      "Longtemnps",
      "Tiens"
    ]
  },
  "ID 21": {
    "Centro\u00efde": "Maintenant",
    "Freq. centroide": 4,
    "Termes": [
      "Abandonnant",
      "Maintenant",
      "Mainteuant"
    ]
  },
  "ID 22": {
    "Centro\u00efde": "Proscrit",
    "Freq. centroide": 35,
    "Termes": [
      "Poscrit",
      "Poserit",
      "Procrit",
      "Proscrit",
      "Proscrit.-",
      "Proserit",
      "Prosorit",
      "Prossrit",
      "Pvoscrit",
      "Pyoscrilten",
      "Roproduction"
    ]
  },
  "ID 23": {
    "Centro\u00efde": "d'Espagne",
    "Freq. centroide": 2,
    "Termes": [
      "Espagnol",
      "d'Espagne"
    ]
  },
  "ID 24": {
    "Centro\u00efde": "Vene",
    "Freq. centroide": 1,
    "Termes": [
      "Asie",
      "Ben",
      "Bien-Aime",
      "Ferney",
      "Penez",
      "Silencel",
      "Tenez",
      "Vene",
      "Venez",
      "Venise",
      "Verdute",
      "Vgue",
      "Vienne",
      "Vire",
      "Vive",
      "eEe",
      "lUne"
    ]
  },
  "ID 25": {
    "Centro\u00efde": "zE",
    "Freq. centroide": 1,
    "Termes": [
      "2E",
      "FE",
      "Gzrt",
      "PEU",
      "P\u017f",
      "REI",
      "ZE",
      "aE",
      "mgE",
      "prE",
      "xeE",
      "xzE",
      "zAMI",
      "zE",
      "zEZ",
      "zGE",
      "zI",
      "zL",
      "zZ",
      "zggE",
      "zxE",
      "zzE",
      "zzEI"
    ]
  },
  "ID 26": {
    "Centro\u00efde": "Lesindividus",
    "Freq. centroide": 1,
    "Termes": [
      "Lesindividus"
    ]
  },
  "ID 27": {
    "Centro\u00efde": "Laisse",
    "Freq. centroide": 3,
    "Termes": [
      "Dliaie",
      "Iaiblesse",
      "Iisse",
      "Laisse",
      "Laissez",
      "Laissons",
      "Legibie",
      "Lisez",
      "Louisiane",
      "Maishtez",
      "Maispeu"
    ]
  },
  "ID 28": {
    "Centro\u00efde": "I--",
    "Freq. centroide": 1,
    "Termes": [
      "A--",
      "Du-",
      "E--",
      "Ea--",
      "FW2",
      "I'---",
      "I-",
      "I--",
      "I-.-",
      "IE-",
      "II-",
      "IL-",
      "I].",
      "Ih-",
      "Ii--",
      "Ime",
      "P--",
      "ae--",
      "ee--",
      "ii--",
      "is:--"
    ]
  },
  "ID 29": {
    "Centro\u00efde": "lLe",
    "Freq. centroide": 4,
    "Termes": [
      "Alle",
      "Aseg",
      "CGe",
      "ILes",
      "Ovea",
      "Pylade",
      "aLE",
      "lBien",
      "lDe",
      "lEh",
      "lEn",
      "lEt",
      "lIe",
      "lL.",
      "lLA",
      "lLI",
      "lLa",
      "lLe",
      "lLtes",
      "lTa"
    ]
  },
  "ID 30": {
    "Centro\u00efde": "II\nI\n\nI\n\n",
    "Freq. centroide": 1,
    "Termes": [
      "As\n\nx\nH\n\nA",
      "II\n\nH\nI\n\n",
      "II\nI\n\nHIII\n",
      "II\nI\n\nI\n\n",
      "L\n\nI\n\nIR\n\n",
      "vI\n\nU\nI\n\nI\n\n"
    ]
  },
  "ID 31": {
    "Centro\u00efde": "mademoiselle",
    "Freq. centroide": 1,
    "Termes": [
      "mademoiselle"
    ]
  },
  "ID 32": {
    "Centro\u00efde": "LASURPR1SE",
    "Freq. centroide": 1,
    "Termes": [
      "LASURPR1SE"
    ]
  },
  "ID 33": {
    "Centro\u00efde": "G----arr:---a----",
    "Freq. centroide": 1,
    "Termes": [
      "G----arr:---a----"
    ]
  },
  "ID 34": {
    "Centro\u00efde": "Pardieul",
    "Freq. centroide": 1,
    "Termes": [
      "Paisienl",
      "Pardieul",
      "Pardilil"
    ]
  },
  "ID 35": {
    "Centro\u00efde": "iaGaLZEiL--.------------",
    "Freq. centroide": 1,
    "Termes": [
      "iaGaLZEiL--.------------"
    ]
  },
  "ID 36": {
    "Centro\u00efde": "lie\n\na\n\na\n\noueieiesee",
    "Freq. centroide": 1,
    "Termes": [
      "lie\n\na\n\na\n\noueieiesee"
    ]
  },
  "ID 37": {
    "Centro\u00efde": "Nl",
    "Freq. centroide": 4,
    "Termes": [
      "Al",
      "BR",
      "Bl",
      "Dl",
      "El",
      "Esl",
      "G\n",
      "Hl",
      "Ll",
      "Ml",
      "N-",
      "NI",
      "NL",
      "NR",
      "NY",
      "Nh",
      "Nl",
      "Nlck",
      "Non",
      "Nonpasl",
      "Nul",
      "Pl",
      "Rl",
      "alP"
    ]
  },
  "ID 38": {
    "Centro\u00efde": "Fe.-.-.ux.glth",
    "Freq. centroide": 1,
    "Termes": [
      "Fe.-.-.ux.glth"
    ]
  },
  "ID 39": {
    "Centro\u00efde": "Pales",
    "Freq. centroide": 1,
    "Termes": [
      "Droles",
      "Iuces",
      "James",
      "Maleval",
      "Misvables",
      "Pales",
      "Parez",
      "Paris",
      "Pas",
      "Pavenu",
      "Pdldu",
      "Phoebus",
      "Pilma",
      "Placee",
      "Ples",
      "Waldeck",
      "brul6s",
      "buffalos",
      "laclEri"
    ]
  },
  "ID 40": {
    "Centro\u00efde": "Angleterre",
    "Freq. centroide": 5,
    "Termes": [
      "Anglelterre",
      "Angleterre"
    ]
  },
  "ID 41": {
    "Centro\u00efde": "Me",
    "Freq. centroide": 1,
    "Termes": [
      "Aae",
      "Cest",
      "De",
      "He",
      "IMe",
      "M-",
      "M4l",
      "MI",
      "MM.",
      "Me",
      "Mnse",
      "Mt",
      "Mu",
      "Mve",
      "Z0",
      "Ze",
      "aMh",
      "eeE",
      "geL",
      "iMk",
      "pEpe"
    ]
  },
  "ID 42": {
    "Centro\u00efde": "Etait",
    "Freq. centroide": 1,
    "Termes": [
      "Ennai",
      "Ensuite",
      "Esprit",
      "Et'UI",
      "Etait",
      "Etats-Unis",
      "lEtit"
    ]
  },
  "ID 43": {
    "Centro\u00efde": "Z5GaEEC.L:-,--ees",
    "Freq. centroide": 1,
    "Termes": [
      "Z5GaEEC.L:-,--ees"
    ]
  },
  "ID 44": {
    "Centro\u00efde": "J'aitort",
    "Freq. centroide": 2,
    "Termes": [
      "Anticosti",
      "J'accourus",
      "J'airecu",
      "J'aitort",
      "J'attends",
      "L'Ecriture"
    ]
  },
  "ID 45": {
    "Centro\u00efde": "Anglais",
    "Freq. centroide": 36,
    "Termes": [
      "Aiglais",
      "Algonquins",
      "Anglais",
      "Anglaisl"
    ]
  },
  "ID 46": {
    "Centro\u00efde": "Sans-Piste",
    "Freq. centroide": 2,
    "Termes": [
      "Ponce-Pilate",
      "Sans-Pisle",
      "Sans-Piste"
    ]
  },
  "ID 47": {
    "Centro\u00efde": "Celle",
    "Freq. centroide": 5,
    "Termes": [
      "Belle",
      "Camillet",
      "Castille",
      "Celle",
      "Celles",
      "Celte",
      "Celtte",
      "Cholula",
      "Creole",
      "Eulln",
      "Ilelle",
      "Jcceple",
      "Speclacle",
      "Telles"
    ]
  },
  "ID 48": {
    "Centro\u00efde": "LiL--.-----.---a---.-----a-----=i-------------------------------------eae=ir=-=re",
    "Freq. centroide": 1,
    "Termes": [
      "LiL--.-----.---a---.-----a-----=i-------------------------------------eae=ir=-=re"
    ]
  },
  "ID 49": {
    "Centro\u00efde": "golfeduMexique",
    "Freq. centroide": 1,
    "Termes": [
      "golfeduMexique"
    ]
  },
  "ID 50": {
    "Centro\u00efde": "L'Aigle-Nolanl",
    "Freq. centroide": 1,
    "Termes": [
      "L'Aigle-Nolanl"
    ]
  },
  "ID 51": {
    "Centro\u00efde": "LLLLLL\n",
    "Freq. centroide": 1,
    "Termes": [
      "LLLLI\n",
      "LLLLL-.LLL",
      "LLLLLL\n"
    ]
  },
  "ID 52": {
    "Centro\u00efde": "aS",
    "Freq. centroide": 1,
    "Termes": [
      "ES",
      "Fo",
      "R\n",
      "RS",
      "ZZ",
      "aAg",
      "aAh",
      "aC",
      "aGG",
      "aI",
      "aR",
      "aS",
      "aT",
      "ae-\u00ac",
      "akS",
      "arr8ta",
      "dS",
      "fSa",
      "iSi",
      "lEai",
      "mP",
      "paS",
      "sS",
      "xP"
    ]
  },
  "ID 53": {
    "Centro\u00efde": "IBLLLlLRIV1hE\n\n",
    "Freq. centroide": 1,
    "Termes": [
      "IBLLLlLRIV1hE\n\n"
    ]
  },
  "ID 54": {
    "Centro\u00efde": "w------------L",
    "Freq. centroide": 1,
    "Termes": [
      "CCC----------=",
      "LAn------:-L",
      "LLe-------------",
      "Le----L.----",
      "Lt2-e---:-------",
      "e---------e--",
      "i------------------5",
      "r----------------ENgA",
      "w------------L"
    ]
  },
  "ID 55": {
    "Centro\u00efde": "Pardonnez",
    "Freq. centroide": 4,
    "Termes": [
      "Padonnez",
      "Pardon",
      "Pardonne",
      "Pardonnez",
      "Pardonnezl",
      "Precedez"
    ]
  },
  "ID 56": {
    "Centro\u00efde": "notresBelle-IRlivire",
    "Freq. centroide": 1,
    "Termes": [
      "notresBelle-IRlivire"
    ]
  },
  "ID 57": {
    "Centro\u00efde": "Bois-lracy",
    "Freq. centroide": 1,
    "Termes": [
      "Bois-Tacy",
      "Bois-Tracy",
      "Bois-l'racy",
      "Bois-lracy",
      "Bois-lracyl",
      "Bois-raey"
    ]
  },
  "ID 58": {
    "Centro\u00efde": "Cetes",
    "Freq. centroide": 1,
    "Termes": [
      "1'etat",
      "Bastel",
      "Certes",
      "Certesl",
      "Cetes",
      "Cher",
      "Createur",
      "Descates",
      "Dites",
      "Etes",
      "Hesites",
      "Restez",
      "Rouges",
      "Seses",
      "cce+e6f"
    ]
  },
  "ID 59": {
    "Centro\u00efde": "Pittsbourg",
    "Freq. centroide": 1,
    "Termes": [
      "Pittsbourg"
    ]
  },
  "ID 60": {
    "Centro\u00efde": "sAwaarassFn.(ge",
    "Freq. centroide": 1,
    "Termes": [
      "sAwaarassFn.(ge"
    ]
  },
  "ID 61": {
    "Centro\u00efde": "Parfaitementl",
    "Freq. centroide": 1,
    "Termes": [
      "Parfaitement",
      "Parfaitementl"
    ]
  },
  "ID 62": {
    "Centro\u00efde": "I\n\nI\n\n",
    "Freq. centroide": 2,
    "Termes": [
      "C\n\nIWI\n\n",
      "E\n\nl\n\n",
      "I\n\n1\n\nI",
      "I\n\n3\n\n",
      "I\n\nI\n\n",
      "I\n\nI\nI",
      "I.\n\nI\n\n",
      "I1\n\n1\n\n",
      "II\nI\n\n",
      "II\nI\n\n1",
      "Ig\n\nIIL",
      "Ih\n\nI\n\n",
      "L\n\nM\n\n",
      "M\nI\n\n2\nI\nI",
      "N\n\nI\n\ni",
      "N\n\nIII\n",
      "P1\n\n\nEs4\n\n",
      "k\n\nE\nS",
      "n\n\nII\n",
      "\u00ac\n\n\u00ac\u00ac\n\n"
    ]
  },
  "ID 63": {
    "Centro\u00efde": "J'avaisespere",
    "Freq. centroide": 1,
    "Termes": [
      "J'avaisespere"
    ]
  },
  "ID 64": {
    "Centro\u00efde": "Ioissementslugubres",
    "Freq. centroide": 1,
    "Termes": [
      "Ioissementslugubres"
    ]
  },
  "ID 65": {
    "Centro\u00efde": "Y",
    "Freq. centroide": 6,
    "Termes": [
      "D",
      "F",
      "G",
      "IY",
      "J",
      "LY",
      "M",
      "O",
      "Su",
      "T",
      "Ti",
      "WW",
      "WY",
      "Y",
      "Y\n",
      "Y.",
      "Y1",
      "YH",
      "YI",
      "YR",
      "YY",
      "Yc",
      "Z",
      "c",
      "f",
      "tN",
      "uY",
      "\u00ac"
    ]
  },
  "ID 66": {
    "Centro\u00efde": "Or",
    "Freq. centroide": 27,
    "Termes": [
      "Lrn",
      "Mr",
      "Nrrr",
      "O\n",
      "Oi",
      "Oo",
      "Or",
      "Or7",
      "Prc",
      "Rr",
      "VOs",
      "Wurd",
      "crP",
      "irT",
      "srI",
      "srM"
    ]
  },
  "ID 67": {
    "Centro\u00efde": "Vesailles",
    "Freq. centroide": 1,
    "Termes": [
      "Semblables",
      "Versailles",
      "Vesailles",
      "Veuillez",
      "Wossicnires"
    ]
  },
  "ID 68": {
    "Centro\u00efde": "Lacomtesse",
    "Freq. centroide": 9,
    "Termes": [
      "Lacomtesse",
      "Lacomtessede",
      "Lncomtesse"
    ]
  },
  "ID 69": {
    "Centro\u00efde": "IIl",
    "Freq. centroide": 11,
    "Termes": [
      "HIIE",
      "HIIHl",
      "HILl",
      "IIE",
      "III",
      "IIIl",
      "IIT",
      "IIi",
      "IIl",
      "INS",
      "IUIH",
      "Iil",
      "Iils",
      "IttIl",
      "LIIl",
      "LIN",
      "LIv",
      "Pol",
      "Tels",
      "lIl",
      "sIl"
    ]
  },
  "ID 70": {
    "Centro\u00efde": "Deu",
    "Freq. centroide": 1,
    "Termes": [
      "Ame-",
      "Caen",
      "Deja",
      "Deji",
      "Deu",
      "Doue",
      "Peau",
      "Peaux",
      "bDes",
      "cyes",
      "euX",
      "jeJ",
      "seB"
    ]
  },
  "ID 71": {
    "Centro\u00efde": "Andre",
    "Freq. centroide": 6,
    "Termes": [
      "Alerte",
      "Ande",
      "Andre",
      "Andve",
      "Anjou",
      "Engge",
      "Londres",
      "Pendre",
      "surprendre"
    ]
  },
  "ID 72": {
    "Centro\u00efde": "Iorce",
    "Freq. centroide": 1,
    "Termes": [
      "Bordeaux",
      "Forie",
      "Iarche",
      "Ionce",
      "Iorce",
      "Ioret",
      "Iorte",
      "Lorsu'",
      "Sorcier"
    ]
  },
  "ID 73": {
    "Centro\u00efde": "AmericainsduNord",
    "Freq. centroide": 1,
    "Termes": [
      "AmericainsduNord"
    ]
  },
  "ID 74": {
    "Centro\u00efde": "Ouais",
    "Freq. centroide": 2,
    "Termes": [
      "Douterais",
      "Fugais",
      "Inais",
      "Mlais",
      "Mnais",
      "Obeis",
      "Ouais",
      "Quoi7",
      "Soudain",
      "Suis"
    ]
  },
  "ID 75": {
    "Centro\u00efde": "Saint-Laurent",
    "Freq. centroide": 4,
    "Termes": [
      "LeSaint-Laurent",
      "Saint-Laurent"
    ]
  },
  "ID 76": {
    "Centro\u00efde": "Jamais",
    "Freq. centroide": 1,
    "Termes": [
      "Carpio",
      "Desormais",
      "J'ai",
      "J'avais",
      "J'errais",
      "J'obeissais",
      "Jamais",
      "Jamaisune",
      "Jobeis",
      "Satanas",
      "Sympathie"
    ]
  },
  "ID 77": {
    "Centro\u00efde": "Hand",
    "Freq. centroide": 1,
    "Termes": [
      "Amand",
      "Canada",
      "Flmand",
      "Hand",
      "Hand6",
      "Hande",
      "Vaincus",
      "Wad",
      "Ward",
      "lanPol"
    ]
  },
  "ID 78": {
    "Centro\u00efde": "Jebaissailatete",
    "Freq. centroide": 1,
    "Termes": [
      "Jebaissailatete"
    ]
  },
  "ID 79": {
    "Centro\u00efde": "France",
    "Freq. centroide": 11,
    "Termes": [
      "Armandl",
      "Blancs",
      "Etrange",
      "Fance",
      "France",
      "Francef",
      "Francel",
      "Franchement",
      "Franoe1",
      "Grande",
      "Inanque",
      "Irappa",
      "Lufrfastice",
      "diIlerence",
      "laFrance",
      "roideFrance"
    ]
  },
  "ID 80": {
    "Centro\u00efde": "Anse-aux-Marigots",
    "Freq. centroide": 2,
    "Termes": [
      "Anse-aux-Marigots"
    ]
  },
  "ID 81": {
    "Centro\u00efde": "Se\n\n",
    "Freq. centroide": 1,
    "Termes": [
      "A60\n\n",
      "N'\n\n",
      "Pde\n\n",
      "Rs\n\n",
      "S\n\n",
      "SM\n\nW",
      "Se\n\n",
      "Slar\n\n",
      "Te\n\n",
      "aes\n\n",
      "lel\n\n",
      "mer\n\n",
      "pei\n\nI",
      "sae\n\n",
      "yZ\n\n",
      "\u00ac\u00ac\u00ac\u00ac\u00ac\u00ac\n"
    ]
  },
  "ID 82": {
    "Centro\u00efde": "Il\n\n",
    "Freq. centroide": 1,
    "Termes": [
      "1I.\n\n",
      "23\n\n",
      "Dl\n\nMI",
      "El\nE\n\n",
      "I\n\n",
      "I\n\n\n",
      "I.\n\n",
      "I1\n\n",
      "I2\n\n",
      "IL\n\nE",
      "IS\n\nLU",
      "IS\n\nM",
      "IY\n\n",
      "Iayelon",
      "Ii-\n\n",
      "Il\n\n",
      "Il\n\nPEE",
      "I\u017fl\n\n",
      "L2\n\n",
      "LIl\n\n",
      "Ll\n\n",
      "MNL\n\n",
      "Ul\n\n",
      "Yl\n\n",
      "aIL-\n\n",
      "i1\n\n",
      "l\n\n",
      "r1l\n\n",
      "zr\n\n"
    ]
  },
  "ID 83": {
    "Centro\u00efde": "Tonne",
    "Freq. centroide": 1,
    "Termes": [
      "Boune",
      "Domine",
      "Guyenne",
      "Honneur",
      "Ieconnue",
      "Ioisonne",
      "Tonne"
    ]
  },
  "ID 84": {
    "Centro\u00efde": "Nouvelle",
    "Freq. centroide": 11,
    "Termes": [
      "Jumonville",
      "Nouvelle",
      "laNouvelle-"
    ]
  },
  "ID 85": {
    "Centro\u00efde": "I\n\nI",
    "Freq. centroide": 4,
    "Termes": [
      "1\n\nI.",
      "1\n\nK",
      "A\n\n3",
      "A\n\nI",
      "A\n\nt",
      "HI\n\nI",
      "I\n\n2",
      "I\n\n3",
      "I\n\nH",
      "I\n\nI",
      "I\n\nar",
      "I\n\nfI",
      "I\nI",
      "I\nRE",
      "I\nW\nAI",
      "I\nW\nH",
      "I1\n\nI",
      "I1I\nI",
      "IHII",
      "II\n\nI",
      "II\n\nII",
      "II\nI",
      "III\n\nI",
      "IY\nI",
      "IY\nL",
      "Ih\n\nI",
      "IlEI",
      "It1.:I",
      "L\n\nI",
      "L\n\niz",
      "L\nI",
      "M\n\nI",
      "R\n\n3",
      "R\n\nKI",
      "RGYC\nI",
      "S\n\nx",
      "U\n\nI",
      "UG\n\nI",
      "Y\n\n6",
      "ZG::-\n\nI",
      "a\n\nEGI",
      "csGS\n\nII",
      "\u00ac\n\n\u00ac"
    ]
  },
  "ID 86": {
    "Centro\u00efde": "Nullement",
    "Freq. centroide": 3,
    "Termes": [
      "Nullement",
      "incl6ment"
    ]
  },
  "ID 87": {
    "Centro\u00efde": "EEI\n\nE",
    "Freq. centroide": 1,
    "Termes": [
      "EE\n\ner\nE",
      "EEI\n\nE",
      "EEl\n\nHEE",
      "El\nEl\n\nE",
      "HH3\n\nIE",
      "LE2\n\nE",
      "rEI\n\nE"
    ]
  },
  "ID 88": {
    "Centro\u00efde": "Bois",
    "Freq. centroide": 1,
    "Termes": [
      "Bois",
      "Bois-",
      "HBois-",
      "Sois",
      "Soit",
      "Vois",
      "Yous",
      "lBois"
    ]
  },
  "ID 89": {
    "Centro\u00efde": "Puuvrediablel",
    "Freq. centroide": 1,
    "Termes": [
      "Puuvrediablel"
    ]
  },
  "ID 90": {
    "Centro\u00efde": "l1'aiinterroge",
    "Freq. centroide": 1,
    "Termes": [
      "l1'aiinterroge"
    ]
  },
  "ID 91": {
    "Centro\u00efde": "Quebec",
    "Freq. centroide": 20,
    "Termes": [
      "Caudebec",
      "Qubec",
      "Quebec",
      "Quelles",
      "Quels",
      "yce-:c"
    ]
  },
  "ID 92": {
    "Centro\u00efde": "Merci",
    "Freq. centroide": 11,
    "Termes": [
      "LAe-::cL",
      "Merci",
      "Mlerci",
      "Teocalis",
      "merci",
      "z::rc::c"
    ]
  },
  "ID 93": {
    "Centro\u00efde": "Explique",
    "Freq. centroide": 1,
    "Termes": [
      "Explique",
      "Expliquez"
    ]
  },
  "ID 94": {
    "Centro\u00efde": "dire;rampant",
    "Freq. centroide": 1,
    "Termes": [
      "dire;rampant"
    ]
  },
  "ID 95": {
    "Centro\u00efde": "izzzzc:==x====z--",
    "Freq. centroide": 1,
    "Termes": [
      "izzzzc:==x====z--"
    ]
  },
  "ID 96": {
    "Centro\u00efde": "fortDuquesne",
    "Freq. centroide": 39,
    "Termes": [
      "Duquesne",
      "IortDuquesne",
      "fortDuquese",
      "fortDuquesne",
      "fortDuquesnel"
    ]
  },
  "ID 97": {
    "Centro\u00efde": "z:::----crcccc",
    "Freq. centroide": 1,
    "Termes": [
      "z:::----crcccc"
    ]
  },
  "ID 98": {
    "Centro\u00efde": "iimigsgrs::2.G",
    "Freq. centroide": 1,
    "Termes": [
      "iimigsgrs::2.G"
    ]
  },
  "ID 99": {
    "Centro\u00efde": "Couleuvre",
    "Freq. centroide": 15,
    "Termes": [
      "Couleuoe",
      "Couleure",
      "Couleuure",
      "Couleuve",
      "Couleuveleu",
      "Couleuvre",
      "Couleuwre",
      "LaCouleuvre"
    ]
  },
  "ID 100": {
    "Centro\u00efde": "Bois-Brles",
    "Freq. centroide": 3,
    "Termes": [
      "Bois-Ble",
      "Bois-Brles",
      "Bois-Brtles"
    ]
  },
  "ID 101": {
    "Centro\u00efde": "A\nH\n\ngg\nL\n\nI\nI",
    "Freq. centroide": 1,
    "Termes": [
      "A\nH\n\ngg\nL\n\nI\nI"
    ]
  },
  "ID 102": {
    "Centro\u00efde": "SautdeMontmorency",
    "Freq. centroide": 1,
    "Termes": [
      "SautdeMontmorency"
    ]
  },
  "ID 103": {
    "Centro\u00efde": "lLABELLLEIYIERE\n\n",
    "Freq. centroide": 1,
    "Termes": [
      "lLABELLLEIYIERE\n\n"
    ]
  },
  "ID 104": {
    "Centro\u00efde": "Effectivement",
    "Freq. centroide": 2,
    "Termes": [
      "Effectivement"
    ]
  },
  "ID 105": {
    "Centro\u00efde": "baiedesMarmousets",
    "Freq. centroide": 1,
    "Termes": [
      "baiedesMarmousets"
    ]
  },
  "ID 106": {
    "Centro\u00efde": "Ilavgese",
    "Freq. centroide": 1,
    "Termes": [
      "Ilavgese",
      "Itavageuse"
    ]
  },
  "ID 107": {
    "Centro\u00efde": "Nouvelle-Orleans",
    "Freq. centroide": 1,
    "Termes": [
      "Nouvelle-Orleans"
    ]
  },
  "ID 108": {
    "Centro\u00efde": "L-----1",
    "Freq. centroide": 1,
    "Termes": [
      "E----\n\n",
      "EEEcccL----",
      "I.A----e",
      "L-----1",
      "L.LL-----",
      "LLL-----ra",
      "T----Gae",
      "Y-.-----",
      "e--.,---a2\n",
      "e:-----ai",
      "wv---:.-"
    ]
  },
  "ID 109": {
    "Centro\u00efde": "Iauve",
    "Freq. centroide": 1,
    "Termes": [
      "Ia9uves",
      "Iagon",
      "Iauve",
      "Iauves",
      "Imadame",
      "Iume",
      "N'ave",
      "Save",
      "auHavre"
    ]
  },
  "ID 110": {
    "Centro\u00efde": "Ohl",
    "Freq. centroide": 23,
    "Termes": [
      "Chutl",
      "Ehl",
      "L'Ohio",
      "Mol",
      "Oh",
      "Oh1",
      "Ohio",
      "Ohl",
      "Oht",
      "Oll",
      "ihI"
    ]
  },
  "ID 111": {
    "Centro\u00efde": "CONTRECEUR",
    "Freq. centroide": 1,
    "Termes": [
      "CONTRECEUR"
    ]
  },
  "ID 112": {
    "Centro\u00efde": "Iit",
    "Freq. centroide": 4,
    "Termes": [
      "AfiE",
      "Bivar",
      "Dis",
      "IEst",
      "IEt",
      "IIt",
      "Ii1",
      "Iier",
      "Iill",
      "Iini",
      "Iit",
      "Iort",
      "Itt",
      "Iy3",
      "Plt",
      "Poitou",
      "itR",
      "uRt"
    ]
  },
  "ID 113": {
    "Centro\u00efde": "Alleghany",
    "Freq. centroide": 2,
    "Termes": [
      "Alleghany",
      "Alleghanys",
      "Allehany",
      "montsAlleghanys"
    ]
  },
  "ID 114": {
    "Centro\u00efde": "Renad-Bleu",
    "Freq. centroide": 1,
    "Termes": [
      "LeRenard-Bleu",
      "Renad-Bleu",
      "Renad-lBleu",
      "Renard-Bleu"
    ]
  },
  "ID 115": {
    "Centro\u00efde": "eG",
    "Freq. centroide": 1,
    "Termes": [
      "1G\n",
      "Va",
      "aMG",
      "e)fo",
      "eG",
      "eH",
      "geF",
      "iGx",
      "rxG",
      "us",
      "zeG",
      "zzG"
    ]
  },
  "ID 116": {
    "Centro\u00efde": "Ajoutez",
    "Freq. centroide": 2,
    "Termes": [
      "Acceptez",
      "Ajounesl",
      "Ajoutez",
      "Couchez",
      "Prolitez",
      "Redoutez"
    ]
  },
  "ID 117": {
    "Centro\u00efde": "Contre-",
    "Freq. centroide": 1,
    "Termes": [
      "Conaltre",
      "Contre-",
      "Montreal"
    ]
  },
  "ID 118": {
    "Centro\u00efde": "J'aichanged'avis",
    "Freq. centroide": 1,
    "Termes": [
      "J'aichanged'avis"
    ]
  },
  "ID 119": {
    "Centro\u00efde": "Continuez",
    "Freq. centroide": 1,
    "Termes": [
      "Considerez",
      "Continuez",
      "Coulinuez"
    ]
  },
  "ID 120": {
    "Centro\u00efde": "desertlAdieu",
    "Freq. centroide": 1,
    "Termes": [
      "desertlAdieu"
    ]
  },
  "ID 121": {
    "Centro\u00efde": "Traversant",
    "Freq. centroide": 1,
    "Termes": [
      "Ariverons",
      "Traversant",
      "persev6rant"
    ]
  },
  "ID 122": {
    "Centro\u00efde": "Noschevauxl",
    "Freq. centroide": 1,
    "Termes": [
      "Noschevauxl"
    ]
  },
  "ID 123": {
    "Centro\u00efde": "Providenee",
    "Freq. centroide": 1,
    "Termes": [
      "Accidente",
      "Providence",
      "Providenee"
    ]
  },
  "ID 124": {
    "Centro\u00efde": "HE",
    "Freq. centroide": 2,
    "Termes": [
      "H,/g",
      "H1",
      "H2E\n",
      "HE",
      "HE\n",
      "HEl",
      "HI",
      "HK",
      "HL",
      "HM",
      "HSE",
      "IHL",
      "J7",
      "kE",
      "kEn"
    ]
  },
  "ID 125": {
    "Centro\u00efde": "IIIIIIIIIIIIIII\n\n",
    "Freq. centroide": 1,
    "Termes": [
      "IIIIIIIIIIIIIII\n\n"
    ]
  },
  "ID 126": {
    "Centro\u00efde": "E\n\nI\nII",
    "Freq. centroide": 1,
    "Termes": [
      "E\n\n5\n\nI\n",
      "E\n\nI\nHN",
      "E\n\nI\nI",
      "E\n\nI\nII",
      "E\n\nII1",
      "E\n\niI\nxE\nII",
      "Erre\n\nIII",
      "HE\n\ne\nxEg",
      "I\n\nI\nII",
      "L\n\ni\n\nI\n",
      "Ml\n\nII\nIII",
      "N\n\nI\nII",
      "n\n\n1\nI",
      "\u00ac\n\ne\nee"
    ]
  },
  "ID 127": {
    "Centro\u00efde": "Fuyez",
    "Freq. centroide": 1,
    "Termes": [
      "Buvez",
      "Croyez",
      "Frye7",
      "Fuyez",
      "Ouvrez",
      "Savez",
      "Soyez"
    ]
  },
  "ID 128": {
    "Centro\u00efde": "capdesMonts-Peles",
    "Freq. centroide": 1,
    "Termes": [
      "capdesMonts-Peles"
    ]
  },
  "ID 129": {
    "Centro\u00efde": "Amerique",
    "Freq. centroide": 16,
    "Termes": [
      "A1'epoque",
      "Ameique",
      "Americains",
      "Amerique",
      "Atlantique",
      "Mexique",
      "l'Amerique"
    ]
  },
  "ID 130": {
    "Centro\u00efde": "Lajeune",
    "Freq. centroide": 1,
    "Termes": [
      "Fuieuse",
      "LEneffel",
      "Lajeune",
      "Lajeunesse",
      "Lalegende",
      "Lejeunes"
    ]
  },
  "ID 131": {
    "Centro\u00efde": "Virginie",
    "Freq. centroide": 11,
    "Termes": [
      "Dinwidie",
      "Viginie",
      "Virginie",
      "Yirginie",
      "lincendie"
    ]
  },
  "ID 132": {
    "Centro\u00efde": "tEEE\n\n",
    "Freq. centroide": 1,
    "Termes": [
      "EEEI\n\n",
      "EEIIEEE\n\n",
      "IEE\n\n",
      "LEE-\nG",
      "LEEE\nze\n\n",
      "LEGL\n\n",
      "aE\nEE\n\n",
      "tEEE\n\n"
    ]
  },
  "ID 133": {
    "Centro\u00efde": "II\n\n",
    "Freq. centroide": 20,
    "Termes": [
      "1I\n\n",
      "2I\n\n",
      "AI\n\n",
      "EIIe\n\n",
      "I\n\n\nM",
      "I'\n\n",
      "I-\n\n",
      "II\n",
      "II\n\n",
      "II\n\n1",
      "II\n\n306",
      "II\n\nE",
      "II\n\nH",
      "II\nH",
      "II\nI.",
      "II'\n",
      "II.i1",
      "IIE\n\n",
      "III\n",
      "III\n\n",
      "IIIT",
      "IILI\n\n",
      "IIS\n\nL",
      "IIt\n\n",
      "IL\n\n",
      "IMI\n\n",
      "Ia\n\n",
      "Id\n\n",
      "KI\n\n",
      "L-'\n\n",
      "LIII\nE.\n",
      "Ms1\n",
      "gI\n\n",
      "l3\n\n",
      "lX\n\n",
      "r.\n\n",
      "xSIiI\n\nu"
    ]
  },
  "ID 134": {
    "Centro\u00efde": "RIVIERE",
    "Freq. centroide": 3,
    "Termes": [
      "CAUMIERE",
      "CLAIRIERE",
      "DEDYRERES",
      "IYIEnE",
      "R1VIIEIE",
      "RIVIE",
      "RIVIERE",
      "RIY1ERE"
    ]
  },
  "ID 135": {
    "Centro\u00efde": "baied'Hudson",
    "Freq. centroide": 3,
    "Termes": [
      "baied'Hudson"
    ]
  },
  "ID 136": {
    "Centro\u00efde": "E\n\n",
    "Freq. centroide": 19,
    "Termes": [
      "1\n\n",
      "2\n\n",
      "21\n\n",
      "2E\n\nsr7",
      "A\n\n",
      "E\n\n",
      "E\n\n2E",
      "E\n\nC",
      "E\n\nE",
      "E\n\nIR",
      "E\n\nM",
      "E\n\neE",
      "E1\n\n",
      "EE\n\n",
      "Ea\n\n",
      "Ege",
      "El\n\n",
      "El\n\nB",
      "F\n\n",
      "H\n\n",
      "HE\n\n",
      "L\n\n",
      "M\n\n",
      "N\n\n",
      "NE\n\n",
      "R\n\n",
      "W\n\n",
      "Z\n\n",
      "a\n\n",
      "aE\nC",
      "aEL\n\n",
      "e:2\n\n",
      "gE\n\n",
      "i\n\n",
      "i.\n\n",
      "n\n\n",
      "r\n\n",
      "t\n\n",
      "\u00ac\n\ne"
    ]
  },
  "ID 137": {
    "Centro\u00efde": "I\n\nI\n",
    "Freq. centroide": 3,
    "Termes": [
      "A\n\nI\n",
      "E1\n\nI\n",
      "Ei\n\nI\n",
      "I\n\n'N",
      "I\n\nI\n",
      "I\n\nIEE",
      "I\n\ni\n",
      "I1\n\nI\n",
      "IH\n\ne2L.",
      "IY\nI\n",
      "Ii\n\nI.EW",
      "hA\n\nI\n",
      "t\n\nII\nI",
      "t.\n\nh\n"
    ]
  },
  "ID 138": {
    "Centro\u00efde": "comlessedeMalevul",
    "Freq. centroide": 1,
    "Termes": [
      "LacomtessedeMaleval",
      "comlessedeMalevul",
      "imede\nMPdeMaleval"
    ]
  },
  "ID 139": {
    "Centro\u00efde": "C",
    "Freq. centroide": 8,
    "Termes": [
      ".LCE",
      "1N",
      "B",
      "C",
      "C-",
      "CGd",
      "CI",
      "CM",
      "Ca",
      "Co",
      "Cr",
      "E",
      "EC",
      "ECCa",
      "H",
      "LGC",
      "N",
      "P",
      "R",
      "Rg",
      "S",
      "U",
      "UCs",
      "WC",
      "iC",
      "sC",
      "vCF"
    ]
  },
  "ID 140": {
    "Centro\u00efde": "Assassinez",
    "Freq. centroide": 1,
    "Termes": [
      "Assassinez",
      "Mississipi",
      "Spndassin",
      "Voushesitez"
    ]
  },
  "ID 141": {
    "Centro\u00efde": "EEEE",
    "Freq. centroide": 1,
    "Termes": [
      "EEEE",
      "EEESE",
      "EzciccEE2E",
      "IEEEEEIE",
      "LEEE",
      "LEZE22",
      "MELLlE",
      "aeiEEE",
      "au5\nzEEE",
      "eEEE",
      "g;gEE",
      "lEEE",
      "zEEEEE",
      "\u00ac\u00ac\u00ac\u00ac"
    ]
  },
  "ID 142": {
    "Centro\u00efde": "Jusque",
    "Freq. centroide": 1,
    "Termes": [
      "Jerusalem",
      "Jusqu'",
      "Jusque",
      "Losque",
      "Nisage",
      "Ouelques",
      "Risque",
      "Risque-"
    ]
  },
  "ID 143": {
    "Centro\u00efde": "Attendez",
    "Freq. centroide": 6,
    "Termes": [
      "Attendez",
      "Attendezl",
      "Rendez"
    ]
  },
  "ID 144": {
    "Centro\u00efde": "sL",
    "Freq. centroide": 1,
    "Termes": [
      ".2",
      "AL",
      "BL",
      "CL",
      "EL",
      "Gsfi",
      "L",
      "Pasu",
      "RL",
      "ULN",
      "aLl",
      "c-.L",
      "eSL",
      "gK",
      "hsA",
      "msL",
      "pL",
      "rL",
      "sG",
      "sL",
      "saY",
      "ueL",
      "unL",
      "usL"
    ]
  },
  "ID 145": {
    "Centro\u00efde": "BELLERIV1ERE",
    "Freq. centroide": 5,
    "Termes": [
      "BELLERIV1ERE",
      "BELLERIV1IEE",
      "BELLIEIV1EuE",
      "BELLLERIV1EnE",
      "BELLlERIV1LE",
      "BElLLEIIY1EnE",
      "BLLLERIV1ERL",
      "ELLEIV1EnE",
      "ILLIH1V1EIE",
      "lLABELLERIV1RE"
    ]
  },
  "ID 146": {
    "Centro\u00efde": "Frangais",
    "Freq. centroide": 3,
    "Termes": [
      "Fancais",
      "Faneais",
      "Fangais",
      "Franais",
      "Francais",
      "Franeais",
      "Frangais",
      "Iragais",
      "Irancais",
      "LesFrangais",
      "Neanmoins",
      "lesFrangais"
    ]
  },
  "ID 147": {
    "Centro\u00efde": "cr===-====--",
    "Freq. centroide": 1,
    "Termes": [
      "cr===-====--"
    ]
  },
  "ID 148": {
    "Centro\u00efde": "consid6rables",
    "Freq. centroide": 1,
    "Termes": [
      "consid6rables"
    ]
  },
  "ID 149": {
    "Centro\u00efde": "Reprenons",
    "Freq. centroide": 1,
    "Termes": [
      "Cependunt",
      "Jecomprends",
      "Reposons",
      "Reprenez",
      "Reprenons",
      "Reproduclion"
    ]
  },
  "ID 150": {
    "Centro\u00efde": "BELLERIVIERE",
    "Freq. centroide": 1,
    "Termes": [
      "BBLLER1IERE",
      "BBLLERIVIERE",
      "BEILERIVIERE",
      "BELLBI1VIERE",
      "BELLBRIVIERE",
      "BELLBRIVIRE",
      "BELLEIVIEIRL",
      "BELLEIVInRE",
      "BELLER1VIERE",
      "BELLERIVIERE",
      "BELLERIVIERLE",
      "BELLIERIVIER",
      "BELLIERIVIERE\n\n\n\n\n",
      "BELLIIRIVIERE",
      "BELLLER1VIERE",
      "BELLLERIYIERE",
      "BELLLIERIVIERE",
      "BELLlER1YIEE",
      "BELLlERIVI1ERE",
      "DBELLLRIVIERE",
      "ELLERIVIERE",
      "ELLERIYIERE",
      "ELLIERIVIERE"
    ]
  },
  "ID 151": {
    "Centro\u00efde": "BELLIEIYInE",
    "Freq. centroide": 1,
    "Termes": [
      "BBLLEIVInE",
      "BELLBRIYIEE",
      "BELLIEIY1RE",
      "BELLIEIYInE",
      "BELLIERIYILE"
    ]
  },
  "ID 152": {
    "Centro\u00efde": "Manongahela",
    "Freq. centroide": 2,
    "Termes": [
      "Manangahela",
      "Manongahela",
      "Mlanonghahela"
    ]
  },
  "ID 153": {
    "Centro\u00efde": "I1",
    "Freq. centroide": 3,
    "Termes": [
      "AI1S",
      "I",
      "I.",
      "I1",
      "I11",
      "I1d",
      "I2",
      "IA",
      "IJ",
      "IM",
      "INA",
      "IR",
      "IW",
      "IZ",
      "Ia",
      "Ik",
      "Il1",
      "Is",
      "J1",
      "N1",
      "NU1I",
      "Z1",
      "t1"
    ]
  },
  "ID 154": {
    "Centro\u00efde": "Contreceur",
    "Freq. centroide": 5,
    "Termes": [
      "Conteceu",
      "Contrecaeur",
      "Contreceur",
      "Contrecoeu",
      "Contrecosur",
      "EGaEEece---"
    ]
  },
  "ID 155": {
    "Centro\u00efde": "Lucie",
    "Freq. centroide": 1,
    "Termes": [
      "Aucue",
      "Aucune",
      "Julie",
      "L'Aigle",
      "L,,ir",
      "Lucie",
      "Riche",
      "Sicile",
      "s:;cre",
      "soci6te"
    ]
  },
  "ID 156": {
    "Centro\u00efde": "Commentl",
    "Freq. centroide": 1,
    "Termes": [
      "Comentl",
      "Comment'",
      "Commentl",
      "Corbeuf1"
    ]
  },
  "ID 157": {
    "Centro\u00efde": "G'e'---.----.,.-7-'-'",
    "Freq. centroide": 1,
    "Termes": [
      "G'e'---.----.,.-7-'-'"
    ]
  },
  "ID 158": {
    "Centro\u00efde": "Oui",
    "Freq. centroide": 6,
    "Termes": [
      "GZHi",
      "Iugi",
      "Lui",
      "MWi",
      "Muis",
      "OQu'",
      "Oui",
      "Ouie",
      "Sus",
      "hAi",
      "sPi"
    ]
  },
  "ID 159": {
    "Centro\u00efde": "Villiersydeposa",
    "Freq. centroide": 1,
    "Termes": [
      "Villiersydeposa"
    ]
  },
  "ID 160": {
    "Centro\u00efde": "Retire",
    "Freq. centroide": 1,
    "Termes": [
      "Detruisez",
      "New-Yorl",
      "Renard",
      "Retarder",
      "Retire",
      "Reviendrez",
      "Riviere",
      "Veuiueree"
    ]
  },
  "ID 161": {
    "Centro\u00efde": "Iemmes",
    "Freq. centroide": 2,
    "Termes": [
      "IEnsomme",
      "Iemines",
      "Iemme7",
      "Iemmes",
      "Iermee",
      "Quelhommef",
      "Sevres",
      "Sommes"
    ]
  },
  "ID 162": {
    "Centro\u00efde": ".==::=r=:czz",
    "Freq. centroide": 1,
    "Termes": [
      ".==::=r=:czz"
    ]
  },
  "ID 163": {
    "Centro\u00efde": "Lesoleil",
    "Freq. centroide": 2,
    "Termes": [
      "Lesoleil",
      "Lseisiwii",
      "lesoleil",
      "soleil"
    ]
  },
  "ID 164": {
    "Centro\u00efde": "i:::--.---------:------------:a",
    "Freq. centroide": 1,
    "Termes": [
      "i:::--.---------:------------:a"
    ]
  },
  "ID 165": {
    "Centro\u00efde": "EE",
    "Freq. centroide": 7,
    "Termes": [
      "5EE",
      "E.",
      "E3",
      "E6",
      "E7",
      "EE",
      "EEI",
      "EEl",
      "EG",
      "EHI",
      "EI",
      "ELE",
      "EP",
      "ER",
      "EW",
      "EZE:.::Z",
      "Ea",
      "Eau",
      "Ec",
      "Eh",
      "Ei",
      "En",
      "Est",
      "IE",
      "IEE",
      "IELLlE",
      "ME-",
      "St",
      "WE",
      "Zc2ES",
      "gE",
      "lD",
      "mET",
      "nEE",
      "rGE",
      "xEE"
    ]
  },
  "ID 166": {
    "Centro\u00efde": "Iiiltie------LLeer-",
    "Freq. centroide": 1,
    "Termes": [
      "Iiiltie------LLeer-"
    ]
  },
  "ID 167": {
    "Centro\u00efde": "Apres",
    "Freq. centroide": 12,
    "Termes": [
      "AVOSOdes",
      "Aives",
      "Apres",
      "Apres7",
      "Apres`7",
      "Apropos",
      "Aprs",
      "Arrives",
      "Aupres",
      "Avons",
      "Dureste",
      "Emparez",
      "Libres"
    ]
  },
  "ID 168": {
    "Centro\u00efde": "Pilmacommegca",
    "Freq. centroide": 1,
    "Termes": [
      "Pilmacommegca"
    ]
  },
  "ID 169": {
    "Centro\u00efde": "Volant",
    "Freq. centroide": 12,
    "Termes": [
      "Orl6ans",
      "Poussant",
      "Vaiment",
      "Vlant",
      "Volant",
      "Volnt",
      "courant?"
    ]
  },
  "ID 170": {
    "Centro\u00efde": "L\nI\n\nI\nH\nI\n\n",
    "Freq. centroide": 1,
    "Termes": [
      "Hks\n\nI\nI\nI\n\n",
      "L\nI\n\nI\nH\nI\n\n",
      "LI\n\nH\nII\n\nI\n\n",
      "O\nL\n\nI\nL.\n\n'",
      "t\n\nI\n\n3\n\nI\n\n3I"
    ]
  },
  "ID 171": {
    "Centro\u00efde": "chef.rar--",
    "Freq. centroide": 1,
    "Termes": [
      "chef.rar--"
    ]
  },
  "ID 172": {
    "Centro\u00efde": "L-\n\nazE55FE",
    "Freq. centroide": 1,
    "Termes": [
      "L-\n\nazE55FE"
    ]
  },
  "ID 173": {
    "Centro\u00efde": "Eveille",
    "Freq. centroide": 1,
    "Termes": [
      "Eeeeeedde",
      "Enveloppe",
      "Eparpille",
      "Eveille",
      "Levieillard",
      "Suveille",
      "loreille"
    ]
  },
  "ID 174": {
    "Centro\u00efde": "Lamarquise",
    "Freq. centroide": 2,
    "Termes": [
      "Lamarquise",
      "Lnmarquise"
    ]
  },
  "ID 175": {
    "Centro\u00efde": "Jevousecoute",
    "Freq. centroide": 1,
    "Termes": [
      "Jevousecoute"
    ]
  },
  "ID 176": {
    "Centro\u00efde": "pseudo-Indien",
    "Freq. centroide": 1,
    "Termes": [
      "pseudo-Indien"
    ]
  },
  "ID 177": {
    "Centro\u00efde": "Canadien",
    "Freq. centroide": 57,
    "Termes": [
      "Camarades",
      "Canadien",
      "Canadien,-qui",
      "Canadienne",
      "Canadienob6it",
      "Canadiens",
      "Canadieon",
      "Canadions",
      "Canudien",
      "Cauadien",
      "Cnadien",
      "Combien",
      "Cunadien",
      "Enviion"
    ]
  },
  "ID 178": {
    "Centro\u00efde": "Agele",
    "Freq. centroide": 2,
    "Termes": [
      "Accable",
      "Adele",
      "Agele",
      "Agle",
      "Aigle",
      "Amel",
      "Angele",
      "Apeie",
      "Asseyez",
      "Aterre"
    ]
  },
  "ID 179": {
    "Centro\u00efde": "Seigneu",
    "Freq. centroide": 1,
    "Termes": [
      "Joignez",
      "SaSeigneurie",
      "Seigneu",
      "Signe"
    ]
  },
  "ID 180": {
    "Centro\u00efde": "k\n\nESR\n\nIII\nIII",
    "Freq. centroide": 1,
    "Termes": [
      "k\n\nESR\n\nIII\nIII"
    ]
  },
  "ID 181": {
    "Centro\u00efde": "A-\n\n\nE\n\ngggs\n\nIIII",
    "Freq. centroide": 1,
    "Termes": [
      "A-\n\n\nE\n\ngggs\n\nIIII"
    ]
  },
  "ID 182": {
    "Centro\u00efde": "Belle-Riviere",
    "Freq. centroide": 3,
    "Termes": [
      "Belle-Riviere",
      "Belle-Rivire",
      "Belle-liviere"
    ]
  },
  "ID 183": {
    "Centro\u00efde": "II\nIII\n\nI",
    "Freq. centroide": 1,
    "Termes": [
      "II\nII\n\n",
      "II\nII\n\nI",
      "II\nIII\n\n",
      "II\nIII\n\nI",
      "II\nIII\n\ns\n\nI",
      "IIIIIIIIIl",
      "WY\nI\nIII\nI"
    ]
  },
  "ID 184": {
    "Centro\u00efde": "DEI1pUPIILMIA",
    "Freq. centroide": 1,
    "Termes": [
      "DEI1pUPIILMIA"
    ]
  },
  "ID 185": {
    "Centro\u00efde": "L-",
    "Freq. centroide": 4,
    "Termes": [
      "-",
      "A-2",
      "BL-",
      "E-",
      "E7,L.",
      "EL-",
      "F-",
      "H-",
      "K-",
      "L\n",
      "L-",
      "L-==",
      "L1y",
      "L2",
      "L3",
      "LE-",
      "LF",
      "LG",
      "LL-",
      "LM",
      "LR",
      "LZ",
      "Lh",
      "Li",
      "Lm",
      "Ltc:-",
      "Lv",
      "Ly",
      "P,-F",
      "P-",
      "R-",
      "U-",
      "e-e",
      "z-"
    ]
  },
  "ID 186": {
    "Centro\u00efde": "LeProscrit",
    "Freq. centroide": 5,
    "Termes": [
      "LePoscrit",
      "LeProscrit",
      "LeProscrit-",
      "LeProserit"
    ]
  },
  "ID 187": {
    "Centro\u00efde": "LABELLE",
    "Freq. centroide": 2,
    "Termes": [
      "1LABELLE",
      "1LAELLlE",
      "BELLE",
      "L1BELLE",
      "LABELLE",
      "LELEELE",
      "lLABELLE"
    ]
  },
  "ID 188": {
    "Centro\u00efde": "r---",
    "Freq. centroide": 3,
    "Termes": [
      "Na---",
      "e5-es-'--",
      "ecr::-",
      "i---'\n",
      "le--",
      "n---",
      "r---",
      "r----L",
      "r---7",
      "ry--",
      "s---",
      "zc--"
    ]
  },
  "ID 189": {
    "Centro\u00efde": "fortNecessite",
    "Freq. centroide": 5,
    "Termes": [
      "Necessite",
      "fortNcessite",
      "fortNecessite"
    ]
  },
  "ID 190": {
    "Centro\u00efde": "Hurons",
    "Freq. centroide": 1,
    "Termes": [
      "Allons",
      "Esperons",
      "Europe",
      "Europeens",
      "Hurons",
      "Jumon-",
      "Sortons",
      "Voyons",
      "Yoguons"
    ]
  },
  "ID 191": {
    "Centro\u00efde": "II",
    "Freq. centroide": 232,
    "Termes": [
      "AI",
      "EII",
      "GI",
      "HII",
      "I\n",
      "I'",
      "I':g",
      "I.I",
      "I3",
      "II",
      "IIy",
      "IKW",
      "ITI",
      "Ic",
      "Ie",
      "Ig",
      "Ii",
      "Ir",
      "It",
      "Iv",
      "KI",
      "LI",
      "LIY",
      "MII",
      "RI",
      "W2",
      "WI",
      "ZI",
      "aII",
      "alII",
      "eeI",
      "fI",
      "iI",
      "iII",
      "iIs",
      "nI",
      "nII",
      "nUI",
      "rI",
      "tI",
      "teI",
      "uII",
      "unI",
      "v1II",
      "vI",
      "xI",
      "yI"
    ]
  },
  "ID 192": {
    "Centro\u00efde": "A",
    "Freq. centroide": 103,
    "Termes": [
      "4A",
      "A",
      "A\n",
      "A'L",
      "A-",
      "A/.",
      "A4",
      "A6",
      "A7",
      "AA",
      "AP4",
      "AT",
      "Aa",
      "Ah1",
      "Ai",
      "As",
      "GA",
      "K",
      "SO",
      "W",
      "aWA",
      "gO",
      "iA",
      "idA",
      "ilA",
      "\u2019"
    ]
  },
  "ID 193": {
    "Centro\u00efde": "IIIII",
    "Freq. centroide": 5,
    "Termes": [
      "I1IlI1",
      "I3-ceGIII",
      "II\nI\nI",
      "II\nIII",
      "IIIII",
      "IIIIIl",
      "L\n\nIIIII",
      "LIII",
      "U\nIII",
      "WIIIIII",
      "sGEFI"
    ]
  },
  "ID 194": {
    "Centro\u00efde": "chanmiereduProscrit",
    "Freq. centroide": 1,
    "Termes": [
      "chanmiereduProscrit"
    ]
  },
  "ID 195": {
    "Centro\u00efde": "Villies",
    "Freq. centroide": 2,
    "Termes": [
      "Oilogez",
      "Villiers",
      "Villies",
      "Visages"
    ]
  },
  "ID 196": {
    "Centro\u00efde": "J'aitenumapromesse",
    "Freq. centroide": 1,
    "Termes": [
      "J'aitenumapromesse"
    ]
  },
  "ID 197": {
    "Centro\u00efde": "Jesaurairetrouver",
    "Freq. centroide": 1,
    "Termes": [
      "Jesaurairetrouver"
    ]
  },
  "ID 198": {
    "Centro\u00efde": "Opos-",
    "Freq. centroide": 1,
    "Termes": [
      "Opos-",
      "Opossum",
      "Pros-"
    ]
  },
  "ID 199": {
    "Centro\u00efde": "L.--",
    "Freq. centroide": 1,
    "Termes": [
      "L--",
      "L.--",
      "L.--%%",
      "L.-A",
      "L.-r-.L.--",
      "L.a-",
      "L.n",
      "L.zR",
      "LL--7",
      "Lr:--a",
      "Mr,,.-s",
      "a.-s-.-",
      "i.--",
      "i.:-",
      "ii.--"
    ]
  },
  "ID 200": {
    "Centro\u00efde": "Brle",
    "Freq. centroide": 1,
    "Termes": [
      "Bahl1",
      "Berge",
      "Ble",
      "Bref",
      "Brle",
      "Brle7",
      "Grce",
      "Ille",
      "Traey",
      "i2,e",
      "lTrop"
    ]
  },
  "ID 201": {
    "Centro\u00efde": "Ioua",
    "Freq. centroide": 1,
    "Termes": [
      "Acoup",
      "DonJuan",
      "EW3ZFaL",
      "Encouages",
      "IECa",
      "Iaut",
      "Ioua",
      "Iouha",
      "Iouisl",
      "Ioula",
      "Kouha",
      "Tisova"
    ]
  },
  "ID 202": {
    "Centro\u00efde": "xsees:.:rrcce",
    "Freq. centroide": 1,
    "Termes": [
      "xsees:.:rrcce"
    ]
  }
}